adbeventparser/README.MD
adbeventparser/__init__.py
adbeventparser/requirements.txt
adbeventparser/thirdparty.json
adbeventparser-0.10.dist-info/LICENSE.rst
adbeventparser-0.10.dist-info/METADATA
adbeventparser-0.10.dist-info/WHEEL
adbeventparser-0.10.dist-info/top_level.txt
adbeventparser-0.10.dist-info/RECORD
