Metadata-Version: 2.1
Name: adbeventparser
Version: 0.10
Summary: Parses the output from 'uiautomator events' in real time and converts it to a list of lists / pandas DataFrame.
Home-page: https://github.com/hansalemaos/adbeventparser
Author: Johannes Fischer
Author-email: aulasparticularesdealemaosp@gmail.com
License: MIT
Keywords: uiautomator,events,record,adb,android,robo
Classifier: Development Status :: 4 - Beta
Classifier: Programming Language :: Python :: 3 :: Only
Classifier: Programming Language :: Python :: 3.10
Classifier: Topic :: Software Development :: Libraries :: Python Modules
Classifier: Topic :: Utilities
License-File: LICENSE.rst
Requires-Dist: ansi
Requires-Dist: flatten-everything
Requires-Dist: parifinder
Requires-Dist: splitlistatindex
